{
    "feedinfo": {
        "name": "ThreatFox IOC Feed",
        "provider_url": "https://threatfox.abuse.ch",
        "summary": "ThreatFox\uc5d0\uc11c \uc81c\uacf5\ud558\ub294 \ucd5c\uc2e0 \uc545\uc131\ucf54\ub4dc IOC",
        "tech_data": "ThreatFox\uc5d0\uc11c \uc81c\uacf5\ud558\ub294 \uacf5\uac1c \uc704\ud611 \ub370\uc774\ud130",
        "category": "Open Source",
        "icon": "https://threatfox.abuse.ch/static/img/favicon.ico"
    },
    "reports": [
        {
            "id": "threatfox-CyberGate",
            "timestamp": 1742560262,
            "title": "ThreatFox IOC - CyberGate",
            "link": "https://threatfox.abuse.ch/browse.php?search=malware%3ACyberGate",
            "score": 100,
            "iocs": {
                "domain": [
                    "patrick1232.no-ip.biz",
                    "update-microsoft.no-ip.info",
                    "enhanceddomains.no-ip.biz",
                    "hack993.sytes.net",
                    "canadabeta.no-ip.org",
                    "mita.zapto.org",
                    "lawlzorz.no-ip.biz",
                    "hazavit.no-ip.biz",
                    "tahugejrot.no-ip.biz",
                    "barthssss.no-ip.biz",
                    "xbladeinc.zapto.org",
                    "chamta.zapto.org",
                    "thepowerguido.no-ip.biz",
                    "frozenrats.no-ip.org",
                    "sansho007.no-ip.biz",
                    "testy.no-ip.biz",
                    "chamta1.zapto.org",
                    "matrix-zloy.no-ip.biz",
                    "microsoftskype.no-ip.biz",
                    "datasecurity32.no-ip.biz",
                    "minecraft-batlle.servegame.com",
                    "dkcyb.no-ip.org",
                    "dieforfree.no-ip.biz",
                    "ishaqkhan.redirectme.net",
                    "hackthisshit.no-ip.biz",
                    "okaybabe.zapto.org",
                    "best-man.no-ip.org",
                    "pooptit1.no-ip.biz",
                    "cybergatecrack.no-ip.info",
                    "lolbadkid.no-ip.biz",
                    "persis.no-ip.biz",
                    "kakawe2004.no-ip.biz",
                    "checkers-world.no-ip.biz",
                    "m3m0colk.zapto.org",
                    "jacky2020.zapto.org",
                    "forever.no-ip.info",
                    "pinkpanther54.no-ip.org",
                    "jagexfails.zapto.org",
                    "zgogo.no-ip.info",
                    "pleite.no-ip.org",
                    "skikda.sytes.net",
                    "xradox.no-ip.org",
                    "stephie.zapto.org",
                    "susunahi3.no-ip.info",
                    "asment34.no-ip.biz",
                    "efeseaprimera.no-ip.org",
                    "dr-mat.zapto.org",
                    "d1a3l0.no-ip.biz",
                    "locuraaaaaa.zapto.org",
                    "project12222.no-ip.biz",
                    "revennaras.no-ip.org",
                    "susunahi4.no-ip.info",
                    "solidest.dyndns.info",
                    "susunahi1.no-ip.info",
                    "unfor1987.serveftp.net",
                    "xperrtcybergate.no-ip.info",
                    "microsoft1342.no-ip.biz",
                    "troyan-nikos.no-ip.org",
                    "grumpylucas.no-ip.biz",
                    "caveiranegro.no-ip.org",
                    "coderz.no-ip.biz",
                    "a3n-hacker.no-ip.biz",
                    "injector.no-ip.biz",
                    "ihrbekommtmichnie.zapto.org",
                    "lobo-lol.no-ip.biz",
                    "kevinj123.no-ip.org",
                    "morianos.no-ip.org",
                    "morimor72.no-ip.org",
                    "roundbluerobin.no-ip.biz",
                    "jarmen.no-ip.biz",
                    "infectadoemo.no-ip.org",
                    "ken1234.no-ip.info",
                    "cinemaproduction.no-ip.biz",
                    "filehost1.zapto.org",
                    "leopars.no-ip.biz",
                    "egoexxpress.servebbs.net",
                    "khdt2.zapto.org",
                    "raid88rush.myphotos.cc",
                    "salla.no-ip.biz",
                    "chillastube.podzone.org",
                    "no0od.zapto.org",
                    "traphier-traph.serveftp.com",
                    "hackeck.no-ip.info",
                    "ttnet.gotdns.com",
                    "minoip1001.zapto.org",
                    "lamafiahacker.no-ip.org",
                    "snypz.poseidonbot.com",
                    "aytac.zapto.org",
                    "crackear.no-ip.org",
                    "cyberk.no-ip.org",
                    "ph9xlplaunlx150.sytes.net",
                    "hxh.ath.cx",
                    "tysonscape.zapto.org",
                    "darkcomet2.no-ip.biz",
                    "gillamp.no-ip.info",
                    "kptkmm.no-ip.org",
                    "xll.no-ip.info",
                    "obv.no-ip.info",
                    "atlantise.zapto.org",
                    "hackerpool.no-ip.biz",
                    "dietimee.no-ip.org",
                    "asssh2010.no-ip.biz",
                    "mark92.no-ip.biz",
                    "ghostraider.zapto.org",
                    "aptem18.no-ip.biz",
                    "pri1.no-ip.org",
                    "tangodown.no-ip.biz",
                    "arschloch456.no-ip.biz",
                    "lahssen1984.no-ip.biz",
                    "chouchou.no-ip.biz",
                    "gonza09.no-ip.org",
                    "burgy.no-ip.org",
                    "tutorial2016.ddns.net",
                    "wiseagle101.zapto.org",
                    "thepowerguido.no-ip.org",
                    "1337krypton.no-ip.biz",
                    "michaudb.no-ip.biz",
                    "mena.ath.cx",
                    "123qwe.no-ip.org",
                    "intercool.zapto.org",
                    "thisworldiscrazy.no-ip.biz",
                    "sp1ffy.no-ip.biz",
                    "krpt.dyndns.info",
                    "turkkilainen.no-ip.biz",
                    "hacker13.no-ip.org",
                    "korpz1.no-ip.info",
                    "sunral.no-ip.info",
                    "ogeniohacker.no-ip.org",
                    "senhordacaveira.no-ip.org",
                    "msgh.no-ip.biz",
                    "bullseye23.no-ip.biz",
                    "sadvent.no-ip.biz",
                    "tupeoramenaza.zapto.org",
                    "syndrome.servemp3.com",
                    "nwal.zapto.org",
                    "fahadm.no-ip.biz",
                    "cable.cable-modem.org",
                    "proalexpro.no-ip.org",
                    "lodoclan.servegame.com",
                    "jaja1334.zapto.org",
                    "onlycryy.no-ip.biz",
                    "goodalge.zapto.org",
                    "medo99.no-ip.info",
                    "sada.zapto.org",
                    "mstlj.no-ip.biz",
                    "hacker37.zapto.org",
                    "lt1.zapto.org",
                    "t1t4n.no-ip.info",
                    "asas.hopto.org",
                    "ibm30073007.no-ip.org",
                    "poison00.no-ip.org",
                    "darkrounge.no-ip.biz",
                    "5onny.no-ip.biz",
                    "chakra22.zapto.org",
                    "genjitakiya.zapto.org",
                    "susunahi.no-ip.info",
                    "wearethehorde.no-ip.org",
                    "733t.no-ip.org",
                    "nextlogon.no-ip.biz",
                    "number.no-ip.org",
                    "implingfinderv3.zapto.org",
                    "incomingdisaster.no-ip.org",
                    "susunahi2.no-ip.info",
                    "james1990.no-ip.biz",
                    "picudobot.no-ip.org",
                    "fantasmas.no-ip.org",
                    "shniwel0.no-ip.biz",
                    "bakainu.no-ip.info",
                    "raidrush.zapto.org",
                    "runescapemodstaff.no-ip.biz",
                    "grumpyemo.no-no.biz",
                    "meiko-s.no-ip.org",
                    "disgow1.no-ip.org",
                    "godimath.no-ip.org",
                    "microsoftupd.no-ip.info",
                    "derdar.zapto.org",
                    "snowhost.no-ip.biz",
                    "biv3.no-ip.biz"
                ],
                "ip": [
                    "188.49.81.147",
                    "37.72.20.177",
                    "85.216.30.19",
                    "200.85.213.103",
                    "84.240.10.41",
                    "69.116.218.10",
                    "94.209.216.217",
                    "187.61.156.97",
                    "75.127.106.18",
                    "82.242.243.50"
                ]
            }
        },
        {
            "id": "threatfox-Formbook",
            "timestamp": 1742560262,
            "title": "ThreatFox IOC - Formbook",
            "link": "https://threatfox.abuse.ch/browse.php?search=malware%3AFormbook",
            "score": 50,
            "iocs": {
                "domain": [
                    "d-agent.xyz",
                    "zit.world",
                    "egalregistration.net",
                    "evmedia.info",
                    "nuocjpg.info",
                    "reeseotool.pro",
                    "lomail.sbs",
                    "olominer.net",
                    "cosflare.online",
                    "ziugsyw.xyz",
                    "anashekwrites.net",
                    "gents4b.online",
                    "ollectors.legal",
                    "leartec.health",
                    "fine-to-fine.top",
                    "rg-txtagstorefrontfze.world",
                    "sharedbtc.xyz",
                    "digi-well.cloud",
                    "ertifiedfasting.info",
                    "ielosanantonio.online",
                    "ewaraja.xyz",
                    "circling.sbs",
                    "ecafecito.net",
                    "ohnnywilly.tech",
                    "ay-id2299.info",
                    "itchen-remodeling-up.world",
                    "peekr.app",
                    "illionblocks.xyz",
                    "ituttotienda.online",
                    "olourg.irish",
                    "ailyhotdealstoday.world",
                    "fve88.win",
                    "erspirexbrasil.online",
                    "yperfakeverse.xyz",
                    "udes-kitchen.net",
                    "erforbedsets.shop",
                    "rodirectiveconsultinghq.info",
                    "evala.online",
                    "twuytr.online",
                    "radient777.xyz",
                    "eachassistant.xyz",
                    "fluorforesetgambes.cloud",
                    "video-games-39348.bond",
                    "ainiceria.pro",
                    "edopen.net",
                    "wlf.dev",
                    "umidifier-74367.bond",
                    "leganttreasuresboutique.info",
                    "impleq.xyz",
                    "camtech.online",
                    "affiliate-marketing-16056.bond",
                    "elegelhg.qpon",
                    "bjcwedding.xyz",
                    "y-marketing-chef.online",
                    "uaizhan.xyz",
                    "trongmindcheck.today",
                    "ijn-websupport.sbs",
                    "enyore.community",
                    "arkettschleifen-dielen.online",
                    "reameast.live",
                    "ifestylebonus.pro",
                    "2345zxrtvc.homes",
                    "eishininternationalava.shop",
                    "emvmaasbn.pro",
                    "assaumergerfunds.info",
                    "aptops-for-sale.cfd",
                    "yroisland.net",
                    "hufi.pink",
                    "ivepeace.asia",
                    "figment.company",
                    "eliverynacional.online",
                    "aifriendship.store",
                    "spearsplatssplint.cloud",
                    "raveline.tech",
                    "hoangntran.net",
                    "martdrivecare.sbs",
                    "pecoincopilot.xyz",
                    "ovesmaps.online",
                    "lectronics-engineering.cfd",
                    "uslim-dating-iocc5xdbns61.today",
                    "opcorninc.lol",
                    "egreen.green",
                    "sneakershopnowsportsale.shop",
                    "crypt.xyz",
                    "radioplaylist.xyz",
                    "td0t.info",
                    "trsfaa.shop",
                    "ealmsec.info",
                    "irinevlerbombaci.xyz",
                    "odltown.xyz",
                    "bytxop.online",
                    "online-advertising-56759.bond",
                    "partmentflatart.xyz",
                    "nesuns.asia",
                    "itadelot.tech",
                    "cp.fun",
                    "ompresormx1.today",
                    "arlist.app",
                    "onlynaturalpetes.shop",
                    "ravelopedia.info",
                    "sunday.cafe",
                    "nventory-software-45680.bond",
                    "ssetexcelstrongmanageroot.xyz",
                    "oughstorememorial.lifestyle",
                    "akaz-1882.shop",
                    "namensk.info",
                    "aindirectiveteam.info",
                    "nventory-software-91161.bond",
                    "ushgroup.info",
                    "fusowostore.buzz",
                    "v-finance.info",
                    "355.loan",
                    "eleghegl.xyz",
                    "heneapolis.city",
                    "ingchunboxermagazine.net",
                    "lifemeasures.net",
                    "inegameyz.digital",
                    "tarbeat-league.pro",
                    "imorraes.shop",
                    "ndosbobet888.net",
                    "oworking-space-1.live",
                    "co-vision.net",
                    "piccomms.net",
                    "dalang.click",
                    "0ns.pro",
                    "rooutfits.net",
                    "536386.xyz",
                    "ucky-win-spin.xyz",
                    "lp.cash",
                    "ccessibleeyecare.info",
                    "b9s2e.buzz",
                    "appyhere.net",
                    "ureformula.shop",
                    "elegilgh.run",
                    "m128.xyz",
                    "rusthousestyle.sbs",
                    "ar-loans-35530.bond",
                    "88p2p.xyz",
                    "nomy.app",
                    "ictionworks.xyz",
                    "nopickayo.biz",
                    "driel.info",
                    "onstruction-jobs-92972.bond",
                    "avadacasino21.buzz",
                    "ersondigital.shop",
                    "tp-jos178-a2.online",
                    "wiftloom.pics",
                    "77hashrate.xyz",
                    "imilarityapi.xyz",
                    "rodigytools.xyz",
                    "aigeofsage.shop",
                    "oans-credits-73480.bond",
                    "ealdirectiveteam.info",
                    "un20250227-23.fun",
                    "olorityx.info",
                    "ayundevtest.xyz",
                    "viddeos.red",
                    "hatgptstrategies.net",
                    "ferrotypes.yachts",
                    "etnonna.app",
                    "ursing-home-43203.bond",
                    "nipsvuesandbox.studio",
                    "yvalikdigital.online",
                    "uperstash.xyz",
                    "07391.mobi",
                    "lberche.info",
                    "ebatmalam.info",
                    "abianice-warszawska.online",
                    "oodwin-law.cfd",
                    "cremation-services-13702.bond",
                    "reamcloudbright.sbs",
                    "men-health-64737.bond",
                    "antoorschoonmaak-1628796.world",
                    "ilybookstone.shop",
                    "heap-flights-1466962.fyi",
                    "onductlogicpioneergroupfirm.xyz",
                    "rettvollmar.shop",
                    "ofas-district.world",
                    "pscaleluxury.net",
                    "acacovip.bet",
                    "aludmia.info",
                    "avillabandlebattus.cloud",
                    "olar-panel-jobs-13264.bond",
                    "thaum.africa",
                    "aceseek.online",
                    "iverlakes.online",
                    "estaking888.xyz",
                    "nagapa.irish",
                    "pidersandsparrowsgroup.info",
                    "a911.xyz",
                    "osss.shop",
                    "etafusion.tech",
                    "zkcontents.xyz",
                    "arlsjrmenu.net",
                    "exiqkfylkx.sbs",
                    "mybucketwish.net",
                    "intercall.tech",
                    "23t.xyz",
                    "5m4kj.net",
                    "otdrones.shop",
                    "w88link.vip",
                    "58bet.website",
                    "777-dental-implants-au-204.cfd",
                    "99game.xyz",
                    "elegelhg.watch",
                    "3-nine.net",
                    "klopcy.xyz",
                    "ugmentedmap.xyz",
                    "sa-store.online",
                    "cas32.top",
                    "ootball-coaching-40064.bond",
                    "eyond360.xyz",
                    "qsvuss.pics",
                    "magicfurries.shop",
                    "technectar.top",
                    "r33bz.online",
                    "erfrootdarting.shop",
                    "rice-artificial-886827482.click",
                    "botakempire-8.xyz",
                    "ombadillian.net",
                    "ipsexshop.shop",
                    "riferrari.shop",
                    "railers.info",
                    "ad-schandau-cruise1.today",
                    "artinspiration.net",
                    "pt-45.online",
                    "f.delivery",
                    "ava.design",
                    "brflix.online",
                    "upiterassistant.xyz",
                    "warehouse-inventory-39425.bond",
                    "ohnmcafee.xyz",
                    "htravel.net",
                    "5psjco.top",
                    "rendvault.fashion",
                    "nifiedway.sbs",
                    "ouseofisra-el.net",
                    "tyxtpzv.info",
                    "lowavenue.info",
                    "iberdata.xyz",
                    "influencer-marketing-81492.bond",
                    "cenicroutes.net",
                    "p8uatwdpyjgafakp.cyou",
                    "ovepeace-jp.net",
                    "digiprem.tech",
                    "ex-in-wien.net",
                    "on66my.xyz",
                    "uantumnovamind.pro",
                    "awspro4d.net",
                    "68092.legal",
                    "ealthywayzone.online",
                    "usshelter.net",
                    "cyma98.sbs",
                    "owbest.click",
                    "ucien.world",
                    "atoto.online",
                    "ishwasher-jobs-678341.today",
                    "olar-systems-panels-18238.bond",
                    "verythingchat.xyz",
                    "rodigy.world",
                    "motrim.click",
                    "opculturebuzz.info",
                    "enseitool.xyz",
                    "sararossos.realtor",
                    "avenspar.xyz",
                    "ool-tools.xyz",
                    "ersonaai.shop",
                    "nvhotworx.net",
                    "osmetic-packaging-jobs.click",
                    "g100.beauty",
                    "gcitgvop.online",
                    "adenauno1240.online",
                    "welding-jobs-27111.bond",
                    "ypham-japan.shop",
                    "uenstigesofas.today",
                    "anjau2.cfd",
                    "swift.xyz",
                    "epeiroterbesestrepe.cloud",
                    "urumsbicard.net",
                    "romptsdesigns.xyz",
                    "nfmod.net",
                    "lip-injections-74025.bond",
                    "jolve.shop",
                    "acercoffeecompanyava.shop",
                    "usinesposte.cyou",
                    "s2ega.live",
                    "odkacasino-333.buzz",
                    "idscomefirst.online",
                    "italbitez.info",
                    "uefana.biz",
                    "ork-from-home-vn3.click",
                    "urkish-hair-268864660.click",
                    "nnovativeworld.cyou",
                    "ubstrate360.xyz",
                    "personal-loans-51463.bond",
                    "lwinabar.online",
                    "getthelook.app",
                    "epemog.online",
                    "taolishuxia.vip",
                    "ulsedream.online",
                    "riminal-mischief.cfd",
                    "ngin.live",
                    "mallelectricarsgb.bond",
                    "omaine-videlot.net",
                    "uskomaras-gyor.net",
                    "atinafyava.shop",
                    "ndo777login.pro",
                    "ecnipack.click",
                    "eet-new-people-88653.bond",
                    "nequaled-fang.shop",
                    "ental-implants-58831.bond",
                    "ental-care-2762127.fyi",
                    "echstat.xyz",
                    "vitance.digital",
                    "entista-de-urgencia-us.online",
                    "lil.lat",
                    "online-advertising-61202.bond",
                    "lectro-hub.online",
                    "mbeddedcopilot.xyz",
                    "cjams.autos",
                    "istapro.shop",
                    "ravelconverter.net",
                    "89g.lol",
                    "xpat-health-insurance-ng.online"
                ]
            }
        },
        {
            "id": "threatfox-Cobalt Strike",
            "timestamp": 1742560262,
            "title": "ThreatFox IOC - Cobalt Strike",
            "link": "https://threatfox.abuse.ch/browse.php?search=malware%3ACobalt Strike",
            "score": 100,
            "iocs": {
                "ip": [
                    "213.94.218.20",
                    "123.57.37.108",
                    "152.42.185.238",
                    "122.228.214.89",
                    "8.155.6.37",
                    "159.223.6.148",
                    "139.180.190.26",
                    "113.45.128.31",
                    "106.75.174.5",
                    "180.76.138.238",
                    "142.93.234.234",
                    "121.36.215.212",
                    "103.115.18.66",
                    "92.246.87.44",
                    "146.190.255.98",
                    "198.98.56.99",
                    "202.182.122.237",
                    "45.145.229.66",
                    "171.43.169.214",
                    "159.65.205.212",
                    "113.44.87.199",
                    "111.229.78.104",
                    "202.79.169.37",
                    "164.92.166.25",
                    "134.209.197.99",
                    "101.132.243.241",
                    "154.8.160.34",
                    "101.133.157.22",
                    "47.93.28.103",
                    "42.51.40.85",
                    "202.79.169.126",
                    "113.125.100.178",
                    "42.51.40.5",
                    "124.221.41.140",
                    "213.94.218.16",
                    "217.156.50.139",
                    "120.24.64.74",
                    "60.204.225.39",
                    "119.188.172.147",
                    "121.41.63.119",
                    "44.203.159.29",
                    "148.66.2.197",
                    "114.55.234.138",
                    "120.53.240.136",
                    "159.223.232.3",
                    "159.89.190.100",
                    "120.78.65.206",
                    "139.9.135.76",
                    "178.128.247.77",
                    "47.108.149.149",
                    "196.251.72.250",
                    "91.208.197.28",
                    "154.205.157.83",
                    "60.204.218.12",
                    "60.204.144.169",
                    "139.9.92.182",
                    "39.106.38.44",
                    "3.75.243.103",
                    "47.120.1.219",
                    "111.124.194.229",
                    "192.241.195.81",
                    "1.94.105.194",
                    "101.33.122.244",
                    "154.82.92.133",
                    "139.196.181.1",
                    "3.82.243.255",
                    "213.252.247.226",
                    "8.148.20.113",
                    "39.104.25.13",
                    "107.174.127.130",
                    "39.100.77.190",
                    "159.138.35.127",
                    "51.210.150.70",
                    "101.33.209.114",
                    "47.92.204.3",
                    "115.126.83.121",
                    "124.221.117.90",
                    "82.156.145.11",
                    "182.242.63.203",
                    "113.44.90.0",
                    "47.121.123.96",
                    "114.132.186.106",
                    "110.41.147.219",
                    "20.74.209.192",
                    "39.100.70.46",
                    "172.86.80.66",
                    "47.97.84.155",
                    "120.26.122.132",
                    "139.59.99.124",
                    "152.136.17.91",
                    "51.79.249.202",
                    "42.194.139.66",
                    "47.97.73.88",
                    "35.231.55.62",
                    "124.222.38.4",
                    "52.68.47.107",
                    "101.34.243.38",
                    "38.55.232.120",
                    "16.62.96.40",
                    "49.232.143.137",
                    "173.232.146.69",
                    "198.12.121.168",
                    "47.116.208.81",
                    "20.83.148.22",
                    "109.172.7.62",
                    "111.230.212.37",
                    "54.37.226.59",
                    "209.38.33.149",
                    "192.9.159.128",
                    "118.31.221.93",
                    "116.205.237.158",
                    "107.175.30.227",
                    "135.237.137.54",
                    "165.22.199.11",
                    "109.73.207.115",
                    "8.137.15.87",
                    "45.77.29.113",
                    "42.51.39.226",
                    "47.116.181.251",
                    "172.203.216.225",
                    "60.204.244.23",
                    "60.205.5.44",
                    "172.98.23.97",
                    "117.72.123.75",
                    "47.108.63.64",
                    "47.239.148.18",
                    "120.26.226.30",
                    "47.93.33.30",
                    "139.159.187.200",
                    "213.94.218.22",
                    "1.92.100.58",
                    "185.208.158.227",
                    "106.75.224.31",
                    "47.253.165.251",
                    "110.172.104.95",
                    "74.176.106.50",
                    "156.238.233.109",
                    "124.221.32.87",
                    "119.23.149.26",
                    "106.14.126.40",
                    "192.3.105.209",
                    "128.199.45.151",
                    "107.189.2.38",
                    "196.251.70.183",
                    "117.72.34.54",
                    "54.216.72.51",
                    "129.211.219.64",
                    "39.105.11.167",
                    "121.37.221.98",
                    "124.222.152.64",
                    "84.201.174.9",
                    "27.152.185.86",
                    "150.158.80.227",
                    "101.43.252.53",
                    "124.225.167.244",
                    "39.106.137.224",
                    "20.163.145.194",
                    "209.38.33.44",
                    "202.79.169.55",
                    "43.156.101.186",
                    "152.42.128.44",
                    "111.230.30.197",
                    "88.218.93.54",
                    "113.44.48.28",
                    "8.141.95.197",
                    "104.42.26.171",
                    "148.66.2.195",
                    "42.51.44.204",
                    "39.108.176.121",
                    "146.190.237.123",
                    "113.44.194.13",
                    "13.200.162.35",
                    "36.213.31.77",
                    "1.95.212.120",
                    "104.168.15.54",
                    "148.66.2.194",
                    "83.219.250.119",
                    "47.112.118.101",
                    "113.44.73.159"
                ],
                "domain": [
                    "microsofts.wiki",
                    "dongfangshuye.xyz",
                    "code47.amazehome.xyz",
                    "vozaspecial.com",
                    "apply.bluehighland-finance.com",
                    "adm.dreamad.mobi",
                    "cngov-gov-xejpcmqhyb.cn-shanghai.fcapp.run",
                    "lmyz.yiqing99.cn",
                    "oversizes.ghostgames.mom",
                    "a-0001.a2-msedge.net",
                    "1329742111-h1rmesk2t.ap-guangzhou.tencentscf.com",
                    "cngov.oss-cn-shanghai.aliyuncs.com"
                ]
            }
        },
        {
            "id": "threatfox-DarkComet",
            "timestamp": 1742560262,
            "title": "ThreatFox IOC - DarkComet",
            "link": "https://threatfox.abuse.ch/browse.php?search=malware%3ADarkComet",
            "score": 100,
            "iocs": {
                "domain": [
                    "b0b1.zapto.org",
                    "nillumronnoc.no-ip.biz",
                    "darwerft.no-ip.info",
                    "wwws.zapto.org",
                    "vaghavethepower.no-ip.biz",
                    "nervernvm.zapto.org",
                    "peelsupport.no-ip.org",
                    "fail-rat.zapto.org",
                    "bitz.servepics.com",
                    "st33lc1tyf4n.zapto.org",
                    "eman.no-ip.info",
                    "celp.zapto.org",
                    "bekiap3332424.sytes.net",
                    "galitma12.zapto.org",
                    "18479.3322.org",
                    "00000.zapto.org",
                    "syricounette.no-ip.biz",
                    "pablit89.no-ip.biz",
                    "zagazoo.zapto.org",
                    "dnse.zapto.org",
                    "deanlet.no-ip.biz",
                    "steamacc123.no-ip.biz",
                    "tswans.no-ip.org",
                    "shahruz007n.no-ip.info",
                    "kgsoloman5000.no-ip.biz",
                    "351625.zapto.org",
                    "cinar12322.zapto.org",
                    "iberat2012.no-ip.org",
                    "roobinos.no-ip.biz",
                    "dannyisadon.no-ip.biz",
                    "serveftm.serveftp.com",
                    "testconnect.no-ip.org",
                    "indeednewb.no-ip.biz",
                    "jakeykid.no-ip.org",
                    "darkcomethiday.no-ip.org",
                    "vegasredbull.no-ip.biz",
                    "newzath.no-ip.org",
                    "jbsoloman5000.no-ip.biz",
                    "korabika.no-ip.org",
                    "opsec.mine.nu",
                    "darkhelper.no-ip.biz",
                    "doulnulla.serveblog.net",
                    "maxiserp.no-ip.biz",
                    "dcownz1.no-ip.org",
                    "hnoo0oody.zapto.org",
                    "jacksonmayjones.zapto.org",
                    "cr4nk1337.no-ip.org",
                    "darwerft.no-ip.org",
                    "roobinosratlocal.no-ip.biz",
                    "vikky38.no-ip.biz",
                    "darkcomet2011.no-ip.org",
                    "wow-ftw.no-ip.org",
                    "mrgenuis.no-ip.org",
                    "suloname.no-ip.info",
                    "hammatov.no-ip.org",
                    "myftp.homeftp.net",
                    "pazuzu11.zapto.org",
                    "ladladladladlad.no-ip.org",
                    "jehadpal10.no-ip.biz",
                    "rattatattat.no-ip.biz",
                    "cheeseburger.no-ip.biz",
                    "jakeyboy159.no-ip.org",
                    "lovemoon93.dyndns-ip.com",
                    "cacaj.no-ip.biz",
                    "facebook-abuse.tk",
                    "logo1212.no-ip.biz",
                    "kam3leon.no-ip.biz",
                    "shizo1337.zapto.org",
                    "xfuego.no-ip.org",
                    "devils-hackers.no-ip.org",
                    "ihacker.dnsd.me",
                    "msaudio.servemp3.com",
                    "rfox.no-ip.biz",
                    "everemete.zapto.org",
                    "waleed-hakerz.no-ip.biz",
                    "sdat.no-ip.biz",
                    "xxyyzz.no-ip.biz",
                    "snarglozog.zapto.org",
                    "fredchen.gotdns.ch",
                    "amjay.myftp.biz",
                    "emirhan-rat1.no-ip.biz",
                    "hostmaster.no-ip.org",
                    "nicksdcrat1.no-ip.org",
                    "kann.no-ip.biz",
                    "fanbase.no-ip.org",
                    "teknohd.no-ip.org",
                    "ultimata.no-ip.org",
                    "bole93.no-ip.org",
                    "bspeanut.no-ip.org",
                    "zxzakozxz.no-ip.org",
                    "finga.no-ip.biz",
                    "dannydanny.zapto.org",
                    "fangtbn.no-ip.org",
                    "jelixhff.no-ip.org",
                    "fytyrlybri2323.zapto.org",
                    "4mph33.no-ip.org",
                    "0000.ole32.com",
                    "aha76.no-ip.biz",
                    "windowshaxor.no-ip.org"
                ],
                "ip": [
                    "77.120.29.157",
                    "72.39.80.238",
                    "108.34.128.228",
                    "85.113.180.44",
                    "5.252.74.203",
                    "109.116.210.232",
                    "79.183.169.134",
                    "31.223.6.8",
                    "200.98.174.142",
                    "84.143.193.35",
                    "173.249.217.23",
                    "185.246.113.247",
                    "109.154.48.141",
                    "62.45.180.50",
                    "91.234.104.220",
                    "98.222.26.73",
                    "95.168.194.192",
                    "86.76.24.22"
                ]
            }
        },
        {
            "id": "threatfox-Mirai",
            "timestamp": 1742560262,
            "title": "ThreatFox IOC - Mirai",
            "link": "https://threatfox.abuse.ch/browse.php?search=malware%3AMirai",
            "score": 100,
            "iocs": {
                "ip": [
                    "195.189.226.165",
                    "104.168.101.27",
                    "185.194.205.79",
                    "46.19.143.10",
                    "95.156.207.88",
                    "23.146.184.61",
                    "104.248.47.182",
                    "195.189.227.167",
                    "185.220.204.227",
                    "209.141.36.93",
                    "92.246.141.75",
                    "51.38.137.108",
                    "196.251.81.246",
                    "2.59.132.84",
                    "45.144.53.177",
                    "23.94.235.18",
                    "103.39.108.224",
                    "107.189.4.201",
                    "45.147.251.145"
                ],
                "domain": [
                    "azmamiraixd.duckdns.org",
                    "botnet.getsolara.info",
                    "bakery.bloggertasher.ru",
                    "250.batcom.top",
                    "bot.gribostress.pro",
                    "data.hello4443.xyz",
                    "botx.tianyadd.top"
                ]
            }
        },
        {
            "id": "threatfox-AsyncRAT",
            "timestamp": 1742560262,
            "title": "ThreatFox IOC - AsyncRAT",
            "link": "https://threatfox.abuse.ch/browse.php?search=malware%3AAsyncRAT",
            "score": 100,
            "iocs": {
                "ip": [
                    "45.200.51.96",
                    "196.251.84.194",
                    "206.123.138.205",
                    "45.92.1.25",
                    "185.93.89.137",
                    "176.65.142.187",
                    "161.97.113.198",
                    "207.244.247.213",
                    "196.251.81.96",
                    "51.89.242.58",
                    "104.245.241.254",
                    "185.254.28.197",
                    "207.231.111.146",
                    "185.206.148.210",
                    "45.200.51.134",
                    "162.243.12.113",
                    "128.90.113.83"
                ],
                "domain": [
                    "lammersville.ddns.net"
                ]
            }
        },
        {
            "id": "threatfox-SpyNote",
            "timestamp": 1742560262,
            "title": "ThreatFox IOC - SpyNote",
            "link": "https://threatfox.abuse.ch/browse.php?search=malware%3ASpyNote",
            "score": 100,
            "iocs": {
                "domain": [
                    "select-as.gl.at.ply.gg",
                    "featured-lt.gl.at.ply.gg",
                    "mr-committees.gl.at.ply.gg",
                    "what-release.gl.at.ply.gg",
                    "worldwide-contributor.gl.at.ply.gg",
                    "adminadmin2023.ddns.net",
                    "est-unfortunately.gl.at.ply.gg",
                    "position-idea.gl.at.ply.gg"
                ],
                "ip": [
                    "154.61.80.208",
                    "46.39.31.25",
                    "103.54.153.7",
                    "103.216.118.53",
                    "194.67.193.20",
                    "46.197.220.52"
                ]
            }
        },
        {
            "id": "threatfox-Unknown malware",
            "timestamp": 1742560262,
            "title": "ThreatFox IOC - Unknown malware",
            "link": "https://threatfox.abuse.ch/browse.php?search=malware%3AUnknown malware",
            "score": 75,
            "iocs": {
                "ip": [
                    "109.123.227.162",
                    "8.130.74.99",
                    "104.248.202.131",
                    "216.176.190.164",
                    "133.218.149.45",
                    "104.37.215.110",
                    "152.53.20.140",
                    "167.86.70.93",
                    "152.228.222.68",
                    "49.13.56.94",
                    "13.234.109.114",
                    "202.146.222.166",
                    "104.248.43.181",
                    "43.202.50.33",
                    "91.121.224.84",
                    "104.37.215.196",
                    "154.12.60.69",
                    "63.177.170.151",
                    "34.128.83.161",
                    "46.235.229.238",
                    "2.58.14.98",
                    "3.99.140.137",
                    "3.139.129.22",
                    "137.184.72.185",
                    "20.244.110.27",
                    "154.12.235.22",
                    "1.15.62.170",
                    "111.31.93.136",
                    "94.242.53.120",
                    "161.35.16.202",
                    "35.247.239.132",
                    "47.100.216.34",
                    "184.82.103.200",
                    "176.126.103.64",
                    "47.79.18.250",
                    "5.182.19.40",
                    "20.40.54.115",
                    "38.242.148.140",
                    "45.155.170.189",
                    "144.22.166.153",
                    "2.58.15.164",
                    "154.9.25.94",
                    "123.136.93.211",
                    "116.181.1.54",
                    "104.37.215.121",
                    "43.160.207.83",
                    "161.35.3.214",
                    "45.226.189.64",
                    "57.129.69.173",
                    "172.105.177.96",
                    "18.193.106.246",
                    "129.28.112.191",
                    "104.37.215.104",
                    "23.160.56.29",
                    "161.35.246.140",
                    "35.77.199.247",
                    "51.75.125.53",
                    "101.32.176.136",
                    "34.148.125.171",
                    "87.251.78.30",
                    "217.77.1.35",
                    "3.142.194.205",
                    "54.211.137.88",
                    "209.38.61.237",
                    "218.17.233.82",
                    "5.75.164.35",
                    "178.128.122.83",
                    "157.90.16.253",
                    "102.117.163.178",
                    "5.34.176.4",
                    "118.195.149.202",
                    "110.43.122.248",
                    "142.93.165.203",
                    "192.253.229.239"
                ],
                "domain": [
                    "ec2-23-20-183-202.compute-1.amazonaws.com",
                    "topclth.click"
                ]
            }
        },
        {
            "id": "threatfox-NjRAT",
            "timestamp": 1742560262,
            "title": "ThreatFox IOC - NjRAT",
            "link": "https://threatfox.abuse.ch/browse.php?search=malware%3ANjRAT",
            "score": 75,
            "iocs": {
                "ip": [
                    "3.126.37.18",
                    "38.54.81.249",
                    "3.121.139.82",
                    "18.198.77.177",
                    "147.185.221.27"
                ],
                "domain": [
                    "8.portmap.host",
                    "pdf-cape.gl.at.ply.gg",
                    "score-fears.gl.at.ply.gg",
                    "size-ingredients.gl.at.ply.gg"
                ]
            }
        },
        {
            "id": "threatfox-PlugX",
            "timestamp": 1742560262,
            "title": "ThreatFox IOC - PlugX",
            "link": "https://threatfox.abuse.ch/browse.php?search=malware%3APlugX",
            "score": 100,
            "iocs": {
                "domain": [
                    "tigernewsmedia.com",
                    "tasensors.com",
                    "createcopilot.com",
                    "alicevivianny.com",
                    "crappienews.com",
                    "redactnews.com",
                    "globaleyenews.com",
                    "antioxidantsnews.com",
                    "meetviberapi.com",
                    "tychonews.com",
                    "mfaicoffice.com",
                    "mrytlebeachinfo.com",
                    "riversidebreakingnews.com",
                    "ivibers.com",
                    "usedownload.com",
                    "reformporta.com",
                    "estmongolia.com",
                    "looksnews.com",
                    "erpdown.com",
                    "sangkayrealnews.com",
                    "maineasce.com",
                    "importsmall.com",
                    "mojhaloton.com",
                    "financialextremed.com",
                    "infotechtelecom.com",
                    "truff-evadee.com",
                    "conflictaslesson.com",
                    "jpkinki.com",
                    "mexicoglobaluniversity.com",
                    "hisnhershealthynhappy.com",
                    "linkonmarketing.com",
                    "newslandtoday.net",
                    "inhller.com",
                    "getfiledown.com",
                    "kerrvillehomeschoolers.com",
                    "quickoffice360.com",
                    "vopaklatinamerica.com",
                    "hajjnewsbd.com",
                    "oncalltechnical.com",
                    "aljazddra.com",
                    "itduniversity.com",
                    "windowsfiledownload.com",
                    "mobilefiledownload.com",
                    "electrictulsa.com",
                    "techoilproducts.com"
                ],
                "ip": [
                    "103.107.105.35",
                    "139.180.192.163",
                    "8.213.237.202",
                    "103.79.120.74"
                ]
            }
        },
        {
            "id": "threatfox-Xtreme RAT",
            "timestamp": 1742560262,
            "title": "ThreatFox IOC - Xtreme RAT",
            "link": "https://threatfox.abuse.ch/browse.php?search=malware%3AXtreme RAT",
            "score": 100,
            "iocs": {
                "domain": [
                    "uae577.no-ip.biz",
                    "balooba-holinlolitago.servegame.com",
                    "kaito.no-ip.org",
                    "hectorr.no-ip.org",
                    "kokaxp.hopto.org",
                    "111111q.no-ip.org",
                    "sophian.no-ip.biz",
                    "bibilomp.servemp3.com",
                    "arabc.no-ip.org",
                    "azert123.no-ip.org",
                    "hdbdg.myftp.biz",
                    "l0opo0l.zapto.org",
                    "fluber12.duckdns.org"
                ],
                "ip": [
                    "27.222.6.49"
                ]
            }
        },
        {
            "id": "threatfox-Bashlite",
            "timestamp": 1742560262,
            "title": "ThreatFox IOC - Bashlite",
            "link": "https://threatfox.abuse.ch/browse.php?search=malware%3ABashlite",
            "score": 100,
            "iocs": {
                "domain": [
                    "autodiscover.a.multi-canale.com",
                    "webdisk.m.web-app-on.com",
                    "webdisk.gestisciweb.com",
                    "cpanel.e.ora-0-web.com",
                    "webdisk.gfjd.104-168-101-27.cprapid.com",
                    "webmail.c.ora-0-web.com",
                    "cpcontacts.web-app-on.com",
                    "cpcalendars.web-app-on.com",
                    "cpcontacts.h.web-app-on.com",
                    "autodiscover.web-app-on.com",
                    "autodiscover.versioneonline.com",
                    "cpanel.f.multi-canale.com",
                    "mail.aaa.104-168-101-27.cprapid.com",
                    "cpanel.continueoraweb.com",
                    "webmail.aa.104-168-101-27.cprapid.com",
                    "cpcontacts.continueoraweb.com",
                    "cpcontacts.b.multi-canale.com",
                    "autodiscover.m.web-app-on.com",
                    "mail.c.multi-canale.com",
                    "autodiscover.e.ora-0-web.com",
                    "mail.e.ora-0-web.com",
                    "cpcontacts.eversioneweb.com",
                    "cpanel.m.web-app-on.com",
                    "webdisk.f.multi-canale.com",
                    "autodiscover.f.multi-canale.com",
                    "webmail.e.multi-canale.com",
                    "webmail.b.ora-0-web.com",
                    "cpcalendars.i.web-app-on.com"
                ],
                "ip": [
                    "46.37.123.142",
                    "94.154.34.34",
                    "192.223.29.160",
                    "45.125.12.175",
                    "176.65.142.137",
                    "212.183.137.12",
                    "103.77.246.204"
                ]
            }
        },
        {
            "id": "threatfox-Sliver",
            "timestamp": 1742560262,
            "title": "ThreatFox IOC - Sliver",
            "link": "https://threatfox.abuse.ch/browse.php?search=malware%3ASliver",
            "score": 50,
            "iocs": {
                "ip": [
                    "75.127.0.221",
                    "24.137.215.157",
                    "191.233.255.35",
                    "194.32.142.52",
                    "147.182.234.126",
                    "104.193.69.145",
                    "82.153.79.9",
                    "5.252.176.71",
                    "143.198.136.6",
                    "45.55.107.101",
                    "92.112.53.234",
                    "144.208.127.129",
                    "196.251.71.174",
                    "64.226.81.244",
                    "165.154.236.59",
                    "8.137.63.19",
                    "52.173.131.28",
                    "177.136.225.140",
                    "104.131.110.130",
                    "64.225.64.178",
                    "167.99.237.18",
                    "103.82.26.172",
                    "119.8.99.254",
                    "185.104.113.254",
                    "103.103.46.12",
                    "167.172.20.102",
                    "156.67.105.193",
                    "162.245.188.151",
                    "142.171.51.88",
                    "212.216.175.143",
                    "159.223.99.145",
                    "2.56.166.131",
                    "51.79.249.202",
                    "43.207.79.213"
                ]
            }
        },
        {
            "id": "threatfox-DeimosC2",
            "timestamp": 1742560262,
            "title": "ThreatFox IOC - DeimosC2",
            "link": "https://threatfox.abuse.ch/browse.php?search=malware%3ADeimosC2",
            "score": 75,
            "iocs": {
                "ip": [
                    "46.232.107.19",
                    "38.150.7.206",
                    "39.185.245.153",
                    "108.207.102.13",
                    "211.138.124.146"
                ]
            }
        },
        {
            "id": "threatfox-Rhadamanthys",
            "timestamp": 1742560262,
            "title": "ThreatFox IOC - Rhadamanthys",
            "link": "https://threatfox.abuse.ch/browse.php?search=malware%3ARhadamanthys",
            "score": 100,
            "iocs": {
                "ip": [
                    "176.65.144.106",
                    "176.65.142.92",
                    "86.54.42.215",
                    "91.240.118.2",
                    "185.208.159.170",
                    "176.65.141.48",
                    "23.94.122.150",
                    "135.181.10.139",
                    "185.196.11.170",
                    "148.135.119.47",
                    "94.156.227.14",
                    "176.65.138.143",
                    "185.208.158.7",
                    "176.65.144.179",
                    "135.181.122.216",
                    "185.245.105.118",
                    "185.208.158.91",
                    "74.117.196.250",
                    "176.65.141.62",
                    "176.65.141.250",
                    "176.65.141.165",
                    "176.65.144.168",
                    "135.181.181.109",
                    "45.125.66.142",
                    "107.189.28.160",
                    "176.65.134.145",
                    "176.65.141.166",
                    "217.156.122.3",
                    "85.158.108.184",
                    "176.65.134.127",
                    "86.54.42.217",
                    "31.172.74.175",
                    "81.19.131.103",
                    "104.37.175.226",
                    "86.54.42.154",
                    "107.175.30.197",
                    "86.54.42.145",
                    "193.124.205.11",
                    "92.60.47.178",
                    "45.150.32.106",
                    "185.196.8.215",
                    "135.181.4.162"
                ],
                "domain": [
                    "bv.yuoei.shop",
                    "playing-music.oss-ap-southeast-7.aliyuncs.com"
                ]
            }
        },
        {
            "id": "threatfox-Havoc",
            "timestamp": 1742560262,
            "title": "ThreatFox IOC - Havoc",
            "link": "https://threatfox.abuse.ch/browse.php?search=malware%3AHavoc",
            "score": 100,
            "iocs": {
                "ip": [
                    "179.43.172.173",
                    "123.56.127.50",
                    "20.51.130.180",
                    "143.198.186.79",
                    "35.177.77.164",
                    "173.237.206.178",
                    "161.35.3.214",
                    "191.13.60.184",
                    "211.25.3.238",
                    "172.86.88.65",
                    "146.190.173.119",
                    "172.86.116.76",
                    "172.191.137.101",
                    "185.5.124.254"
                ],
                "domain": [
                    "210-2-169-213.cprapid.com",
                    "mybkbfpvaixipfsxoa.space",
                    "ec2-3-35-26-26.ap-northeast-2.compute.amazonaws.com"
                ]
            }
        },
        {
            "id": "threatfox-NetSupportManager RAT",
            "timestamp": 1742560262,
            "title": "ThreatFox IOC - NetSupportManager RAT",
            "link": "https://threatfox.abuse.ch/browse.php?search=malware%3ANetSupportManager RAT",
            "score": 50,
            "iocs": {
                "ip": [
                    "54.193.163.62",
                    "35.93.138.89",
                    "54.213.235.215",
                    "54.203.9.92",
                    "3.96.214.65",
                    "100.27.205.78",
                    "15.237.57.60",
                    "54.165.112.96",
                    "13.210.188.96",
                    "176.82.192.80",
                    "13.233.80.253",
                    "50.233.74.170",
                    "54.191.185.125",
                    "54.87.180.125",
                    "34.223.2.188",
                    "18.218.35.184",
                    "3.109.213.193",
                    "130.164.163.76"
                ]
            }
        },
        {
            "id": "threatfox-Lumma Stealer",
            "timestamp": 1742560262,
            "title": "ThreatFox IOC - Lumma Stealer",
            "link": "https://threatfox.abuse.ch/browse.php?search=malware%3ALumma Stealer",
            "score": 100,
            "iocs": {
                "domain": [
                    "triplooqp.world",
                    "starbits.world",
                    "holidamyup.today",
                    "travelilx.top",
                    "battlefie.shop",
                    "advennture.top",
                    "tripzlux.digital",
                    "travewlio.shop",
                    "sighbtseeing.shop",
                    "touvrlane.bet",
                    "soothingpitllow.icu",
                    "esccapewz.run",
                    "flyxaway.live",
                    "beaminduggl.top",
                    "gogetxto.life"
                ]
            }
        },
        {
            "id": "threatfox-Brute Ratel C4",
            "timestamp": 1742560262,
            "title": "ThreatFox IOC - Brute Ratel C4",
            "link": "https://threatfox.abuse.ch/browse.php?search=malware%3ABrute Ratel C4",
            "score": 75,
            "iocs": {
                "ip": [
                    "54.90.212.140"
                ]
            }
        },
        {
            "id": "threatfox-Remcos",
            "timestamp": 1742560262,
            "title": "ThreatFox IOC - Remcos",
            "link": "https://threatfox.abuse.ch/browse.php?search=malware%3ARemcos",
            "score": 100,
            "iocs": {
                "ip": [
                    "45.62.170.96",
                    "45.125.66.57",
                    "66.248.206.248",
                    "176.65.134.7",
                    "172.94.111.240",
                    "45.74.46.34",
                    "68.168.223.108",
                    "186.169.80.207",
                    "37.120.151.102",
                    "172.111.189.21",
                    "194.59.31.69",
                    "172.111.131.195",
                    "206.123.152.41",
                    "135.125.27.232",
                    "176.65.134.39",
                    "80.76.49.130",
                    "196.251.69.85",
                    "216.9.225.133",
                    "91.223.3.141",
                    "72.5.42.161",
                    "95.216.118.42"
                ],
                "domain": [
                    "directlygonow.com",
                    "michelgoodsupportingtems.duckdns.org",
                    "rem9rrr.duckdns.org",
                    "rem9rrr2.duckdns.org",
                    "pipbinorel99.com"
                ]
            }
        },
        {
            "id": "threatfox-ClearFake",
            "timestamp": 1742560262,
            "title": "ThreatFox IOC - ClearFake",
            "link": "https://threatfox.abuse.ch/browse.php?search=malware%3AClearFake",
            "score": 100,
            "iocs": {
                "domain": [
                    "buywellbuysafe.com",
                    "cashcontrol.pe",
                    "check.atuu7.icu",
                    "check.axei3.icu",
                    "allergyad.com",
                    "check.uhaa4.icu",
                    "vegamanagementconsulting.com",
                    "check.aytuna.icu",
                    "serviciosinformaticos.com.co",
                    "creditpronola.com",
                    "check.asiu4.icu"
                ]
            }
        },
        {
            "id": "threatfox-DCRat",
            "timestamp": 1742560262,
            "title": "ThreatFox IOC - DCRat",
            "link": "https://threatfox.abuse.ch/browse.php?search=malware%3ADCRat",
            "score": 100,
            "iocs": {
                "ip": [
                    "112.213.116.35",
                    "148.66.21.234",
                    "148.66.21.237",
                    "5.200.210.1",
                    "110.42.227.156",
                    "85.235.74.114",
                    "148.66.21.236",
                    "45.145.229.196",
                    "154.201.68.239",
                    "176.65.140.20"
                ],
                "domain": [
                    "registration-delayed.gl.at.ply.gg",
                    "co35066.tw1.ru",
                    "27.ip.gl.ply.gg",
                    "advanced-contributing.gl.at.ply.gg",
                    "cut-peripherals.gl.at.ply.gg",
                    "a1104037.xsph.ru",
                    "o-la.gl.at.ply.gg",
                    "a1104094.xsph.ru",
                    "again-duck.gl.at.ply.gg"
                ]
            }
        },
        {
            "id": "threatfox-MooBot",
            "timestamp": 1742560262,
            "title": "ThreatFox IOC - MooBot",
            "link": "https://threatfox.abuse.ch/browse.php?search=malware%3AMooBot",
            "score": 100,
            "iocs": {
                "ip": [
                    "156.229.233.104",
                    "107.172.151.193",
                    "83.168.69.59",
                    "45.144.53.177"
                ]
            }
        },
        {
            "id": "threatfox-Nanocore RAT",
            "timestamp": 1742560262,
            "title": "ThreatFox IOC - Nanocore RAT",
            "link": "https://threatfox.abuse.ch/browse.php?search=malware%3ANanocore RAT",
            "score": 50,
            "iocs": {
                "ip": [
                    "196.251.81.193",
                    "190.159.137.75",
                    "196.251.90.23",
                    "172.94.111.152"
                ]
            }
        },
        {
            "id": "threatfox-Vidar",
            "timestamp": 1742560262,
            "title": "ThreatFox IOC - Vidar",
            "link": "https://threatfox.abuse.ch/browse.php?search=malware%3AVidar",
            "score": 100,
            "iocs": {
                "domain": [
                    "y.p.formaxprime.co.uk"
                ]
            }
        },
        {
            "id": "threatfox-XWorm",
            "timestamp": 1742560262,
            "title": "ThreatFox IOC - XWorm",
            "link": "https://threatfox.abuse.ch/browse.php?search=malware%3AXWorm",
            "score": 50,
            "iocs": {
                "ip": [
                    "38.49.40.130",
                    "193.161.193.99",
                    "147.185.221.25",
                    "100.89.130.98",
                    "3.127.181.115",
                    "45.138.16.211"
                ],
                "domain": [
                    "trumpmelanie.duckdns.org",
                    "0xmicrosoft.duckdns.org",
                    "society-jun.gl.at.ply.gg",
                    "rndik-156-193-90-159.a.free.pinggy.link",
                    "awedfwf-31577.portmap.host",
                    "local-subsidiary.gl.at.ply.gg",
                    "string-cities.gl.at.ply.gg"
                ]
            }
        },
        {
            "id": "threatfox-Venom RAT",
            "timestamp": 1742560262,
            "title": "ThreatFox IOC - Venom RAT",
            "link": "https://threatfox.abuse.ch/browse.php?search=malware%3AVenom RAT",
            "score": 100,
            "iocs": {
                "ip": [
                    "171.232.0.161",
                    "160.191.244.57",
                    "185.196.9.80"
                ]
            }
        },
        {
            "id": "threatfox-FAKEUPDATES",
            "timestamp": 1742560262,
            "title": "ThreatFox IOC - FAKEUPDATES",
            "link": "https://threatfox.abuse.ch/browse.php?search=malware%3AFAKEUPDATES",
            "score": 80,
            "iocs": {
                "domain": [
                    "janhugo.com",
                    "computertecs.com",
                    "loycos.com",
                    "vfclan.co",
                    "scottauto.saxloo.com",
                    "ez-ssb.sipos.services",
                    "vfclan.com",
                    "aoya-kamijichi.info"
                ]
            }
        },
        {
            "id": "threatfox-Orcus RAT",
            "timestamp": 1742560262,
            "title": "ThreatFox IOC - Orcus RAT",
            "link": "https://threatfox.abuse.ch/browse.php?search=malware%3AOrcus RAT",
            "score": 100,
            "iocs": {
                "ip": [
                    "42.119.37.212"
                ]
            }
        },
        {
            "id": "threatfox-Hook",
            "timestamp": 1742560262,
            "title": "ThreatFox IOC - Hook",
            "link": "https://threatfox.abuse.ch/browse.php?search=malware%3AHook",
            "score": 100,
            "iocs": {
                "ip": [
                    "185.100.157.87",
                    "92.118.112.28",
                    "185.100.157.253",
                    "193.149.190.193",
                    "27.124.4.217",
                    "27.124.4.223",
                    "156.253.228.5",
                    "27.124.4.224",
                    "192.238.133.237",
                    "45.207.197.14",
                    "91.214.78.18",
                    "192.238.133.242",
                    "212.86.115.210"
                ],
                "domain": [
                    "mail.efcommxerce.ru",
                    "cpcontacts.efcommxerce.ru"
                ]
            }
        },
        {
            "id": "threatfox-RedLine Stealer",
            "timestamp": 1742560262,
            "title": "ThreatFox IOC - RedLine Stealer",
            "link": "https://threatfox.abuse.ch/browse.php?search=malware%3ARedLine Stealer",
            "score": 100,
            "iocs": {
                "ip": [
                    "135.125.21.41",
                    "104.219.238.26"
                ]
            }
        },
        {
            "id": "threatfox-Unknown RAT",
            "timestamp": 1742560262,
            "title": "ThreatFox IOC - Unknown RAT",
            "link": "https://threatfox.abuse.ch/browse.php?search=malware%3AUnknown RAT",
            "score": 50,
            "iocs": {
                "domain": [
                    "qpkl23.zapto.org",
                    "scbas2.zapto.org",
                    "mktulori.otbhelp.top",
                    "t285.acemisn.win",
                    "iiwq24.zapto.org",
                    "obp316.zapto.org",
                    "kasin22.zapto.org",
                    "grip08r.top",
                    "grtha2.zapto.org",
                    "wbkoliter.exfhelp.top",
                    "rollrer.ylohelp.top",
                    "ityq2nacc.zapto.org",
                    "rnmaor.zapto.org",
                    "q9912ass.ddns.net",
                    "asoso22.zapto.org",
                    "cap569.zapto.org",
                    "mmwerw2.zapto.org",
                    "bbvft221.ddns.net",
                    "sisngl21a.ddns.net",
                    "dsmf3.zapto.org",
                    "trolrte.cgphelp.top",
                    "kghmst32.zapto.org",
                    "oehelp.top",
                    "lotrolnd.jsrhelp.top",
                    "mow929.mvhelp.top",
                    "screensconnct.com",
                    "ommw2.hopto.org",
                    "croisbtg2.zapto.org",
                    "opusns.innoxiously.com"
                ],
                "ip": [
                    "37.221.64.236",
                    "93.157.106.137",
                    "93.157.106.23"
                ]
            }
        },
        {
            "id": "threatfox-Stealc",
            "timestamp": 1742560262,
            "title": "ThreatFox IOC - Stealc",
            "link": "https://threatfox.abuse.ch/browse.php?search=malware%3AStealc",
            "score": 100,
            "iocs": {
                "ip": [
                    "185.184.123.94",
                    "193.68.89.17"
                ]
            }
        },
        {
            "id": "threatfox-SectopRAT",
            "timestamp": 1742560262,
            "title": "ThreatFox IOC - SectopRAT",
            "link": "https://threatfox.abuse.ch/browse.php?search=malware%3ASectopRAT",
            "score": 90,
            "iocs": {
                "domain": [
                    "unrealfabricdo.click",
                    "freemonflask.click",
                    "mail.marketplacelenders.xyz",
                    "usa.webaudiomessages.xyz",
                    "asmitadesign.com"
                ]
            }
        },
        {
            "id": "threatfox-Broomstick",
            "timestamp": 1742560262,
            "title": "ThreatFox IOC - Broomstick",
            "link": "https://threatfox.abuse.ch/browse.php?search=malware%3ABroomstick",
            "score": 50,
            "iocs": {
                "ip": [
                    "206.71.148.172",
                    "168.100.10.165",
                    "64.52.80.96"
                ]
            }
        },
        {
            "id": "threatfox-NetWire RC",
            "timestamp": 1742560262,
            "title": "ThreatFox IOC - NetWire RC",
            "link": "https://threatfox.abuse.ch/browse.php?search=malware%3ANetWire RC",
            "score": 100,
            "iocs": {
                "domain": [
                    "s3awscloud.com"
                ]
            }
        },
        {
            "id": "threatfox-GhostSocks",
            "timestamp": 1742560262,
            "title": "ThreatFox IOC - GhostSocks",
            "link": "https://threatfox.abuse.ch/browse.php?search=malware%3AGhostSocks",
            "score": 100,
            "iocs": {
                "ip": [
                    "91.212.166.154",
                    "91.212.166.155"
                ]
            }
        },
        {
            "id": "threatfox-QakBot",
            "timestamp": 1742560262,
            "title": "ThreatFox IOC - QakBot",
            "link": "https://threatfox.abuse.ch/browse.php?search=malware%3AQakBot",
            "score": 75,
            "iocs": {
                "ip": [
                    "70.31.125.222",
                    "188.4.205.235",
                    "2.88.108.213",
                    "86.190.166.154"
                ]
            }
        },
        {
            "id": "threatfox-Quasar RAT",
            "timestamp": 1742560262,
            "title": "ThreatFox IOC - Quasar RAT",
            "link": "https://threatfox.abuse.ch/browse.php?search=malware%3AQuasar RAT",
            "score": 100,
            "iocs": {
                "ip": [
                    "191.17.127.79",
                    "46.74.133.208",
                    "148.113.214.176",
                    "65.109.133.207",
                    "188.55.210.211"
                ],
                "domain": [
                    "tentyfive5.ydns.eu",
                    "thirtyfive5.ydns.eu",
                    "told-rain.gl.at.ply.gg",
                    "thirtyfive335.crabdance.com"
                ]
            }
        },
        {
            "id": "threatfox-pupy",
            "timestamp": 1742560262,
            "title": "ThreatFox IOC - pupy",
            "link": "https://threatfox.abuse.ch/browse.php?search=malware%3Apupy",
            "score": 100,
            "iocs": {
                "ip": [
                    "70.34.242.59"
                ]
            }
        },
        {
            "id": "threatfox-ShadowPad",
            "timestamp": 1742560262,
            "title": "ThreatFox IOC - ShadowPad",
            "link": "https://threatfox.abuse.ch/browse.php?search=malware%3AShadowPad",
            "score": 50,
            "iocs": {
                "ip": [
                    "108.181.121.150"
                ]
            }
        },
        {
            "id": "threatfox-SquidLoader",
            "timestamp": 1742560262,
            "title": "ThreatFox IOC - SquidLoader",
            "link": "https://threatfox.abuse.ch/browse.php?search=malware%3ASquidLoader",
            "score": 50,
            "iocs": {
                "ip": [
                    "139.224.246.246"
                ]
            }
        },
        {
            "id": "threatfox-MimiKatz",
            "timestamp": 1742560262,
            "title": "ThreatFox IOC - MimiKatz",
            "link": "https://threatfox.abuse.ch/browse.php?search=malware%3AMimiKatz",
            "score": 100,
            "iocs": {
                "ip": [
                    "209.94.59.194",
                    "188.241.240.170"
                ]
            }
        },
        {
            "id": "threatfox-Meterpreter",
            "timestamp": 1742560262,
            "title": "ThreatFox IOC - Meterpreter",
            "link": "https://threatfox.abuse.ch/browse.php?search=malware%3AMeterpreter",
            "score": 75,
            "iocs": {
                "ip": [
                    "172.233.162.232"
                ]
            }
        },
        {
            "id": "threatfox-DOPLUGS",
            "timestamp": 1742560262,
            "title": "ThreatFox IOC - DOPLUGS",
            "link": "https://threatfox.abuse.ch/browse.php?search=malware%3ADOPLUGS",
            "score": 100,
            "iocs": {
                "ip": [
                    "139.84.168.77"
                ],
                "domain": [
                    "getfiledata.com"
                ]
            }
        },
        {
            "id": "threatfox-Eye Pyramid",
            "timestamp": 1742560262,
            "title": "ThreatFox IOC - Eye Pyramid",
            "link": "https://threatfox.abuse.ch/browse.php?search=malware%3AEye Pyramid",
            "score": 75,
            "iocs": {
                "ip": [
                    "194.55.137.39",
                    "194.55.137.38",
                    "65.87.7.138"
                ]
            }
        },
        {
            "id": "threatfox-Unknown Stealer",
            "timestamp": 1742560262,
            "title": "ThreatFox IOC - Unknown Stealer",
            "link": "https://threatfox.abuse.ch/browse.php?search=malware%3AUnknown Stealer",
            "score": 100,
            "iocs": {
                "ip": [
                    "155.138.150.12"
                ]
            }
        },
        {
            "id": "threatfox-Ghost RAT",
            "timestamp": 1742560262,
            "title": "ThreatFox IOC - Ghost RAT",
            "link": "https://threatfox.abuse.ch/browse.php?search=malware%3AGhost RAT",
            "score": 50,
            "iocs": {
                "ip": [
                    "91.4.41.154"
                ]
            }
        },
        {
            "id": "threatfox-Crimson RAT",
            "timestamp": 1742560262,
            "title": "ThreatFox IOC - Crimson RAT",
            "link": "https://threatfox.abuse.ch/browse.php?search=malware%3ACrimson RAT",
            "score": 100,
            "iocs": {
                "ip": [
                    "172.86.109.207"
                ]
            }
        },
        {
            "id": "threatfox-Chaos",
            "timestamp": 1742560262,
            "title": "ThreatFox IOC - Chaos",
            "link": "https://threatfox.abuse.ch/browse.php?search=malware%3AChaos",
            "score": 100,
            "iocs": {
                "ip": [
                    "47.97.178.157"
                ]
            }
        },
        {
            "id": "threatfox-AhMyth",
            "timestamp": 1742560262,
            "title": "ThreatFox IOC - AhMyth",
            "link": "https://threatfox.abuse.ch/browse.php?search=malware%3AAhMyth",
            "score": 50,
            "iocs": {
                "ip": [
                    "197.48.230.161"
                ]
            }
        },
        {
            "id": "threatfox-BlackShades",
            "timestamp": 1742560262,
            "title": "ThreatFox IOC - BlackShades",
            "link": "https://threatfox.abuse.ch/browse.php?search=malware%3ABlackShades",
            "score": 50,
            "iocs": {
                "ip": [
                    "35.180.67.229"
                ]
            }
        },
        {
            "id": "threatfox-DarkVision RAT",
            "timestamp": 1742560262,
            "title": "ThreatFox IOC - DarkVision RAT",
            "link": "https://threatfox.abuse.ch/browse.php?search=malware%3ADarkVision RAT",
            "score": 75,
            "iocs": {
                "ip": [
                    "196.251.72.66"
                ]
            }
        }
    ]
}